Metadata-Version: 2.1
Name: applicationinsights
Version: 0.11.8
Summary: This project extends the Application Insights API surface to support Python.
Home-page: https://github.com/Microsoft/ApplicationInsights-Python
Author: Microsoft
Author-email: appinsightssdk@microsoft.com
License: MIT
Download-URL: https://github.com/Microsoft/ApplicationInsights-Python
Keywords: analytics applicationinsights telemetry appinsights development
Platform: UNKNOWN
Classifier: Development Status :: 3 - Alpha
Classifier: Intended Audience :: Developers
Classifier: Topic :: Software Development :: Libraries :: Python Modules
Classifier: Operating System :: OS Independent
Classifier: License :: OSI Approved :: MIT License
Classifier: Programming Language :: Python :: 2.7
Classifier: Programming Language :: Python :: 3.4
Classifier: Programming Language :: Python :: 3.5
Classifier: Programming Language :: Python :: 3.6
